RuneArtist/__init__.py
RuneArtist/pictures/001.png
RuneArtist/pictures/002.png
RuneArtist/pictures/003.png
RuneArtist/pictures/004.png
RuneArtist/pictures/005.png
RuneArtist/pictures/006.png
RuneArtist/pictures/007.png
RuneArtist/pictures/008.png
RuneArtist/pictures/009.png
RuneArtist/pictures/010.png
RuneArtist/pictures/011.png
RuneArtist/pictures/012.png
RuneArtist/pictures/013.png
RuneArtist/pictures/014.png
RuneArtist/pictures/015.png
RuneArtist/pictures/016.png
RuneArtist/pictures/017.png
RuneArtist/pictures/018.png
RuneArtist/pictures/019.png
RuneArtist/pictures/020.png
RuneArtist/pictures/021.png
RuneArtist/pictures/022.png
RuneArtist/pictures/023.png
RuneArtist/pictures/024.png
RuneArtist/pictures/025.png
RuneArtist/pictures/026.png
RuneArtist/pictures/027.png
RuneArtist/pictures/028.png
RuneArtist/pictures/029.png
RuneArtist/pictures/030.png
RuneArtist/pictures/031.png
RuneArtist/pictures/032.png
RuneArtist/pictures/033.png
RuneArtist/pictures/034.png
RuneArtist/pictures/035.png
RuneArtist/pictures/036.png
RuneArtist/pictures/037.png
RuneArtist/pictures/038.png
RuneArtist-1.0.7.dist-info/METADATA
RuneArtist-1.0.7.dist-info/WHEEL
RuneArtist-1.0.7.dist-info/top_level.txt
RuneArtist-1.0.7.dist-info/RECORD
